ed_domain/__init__.py
ed_domain/common/__init__.py
ed_domain/common/exceptions.py
ed_domain/common/logging.py
ed_domain/common/logs.py
ed_domain/common/singleton_meta.py
ed_domain/core/__init__.py
ed_domain/core/base_domain_object.py
ed_domain/core/aggregate_roots/__init__.py
ed_domain/core/aggregate_roots/admin.py
ed_domain/core/aggregate_roots/auth_user.py
ed_domain/core/aggregate_roots/base_aggregate_root.py
ed_domain/core/aggregate_roots/business.py
ed_domain/core/aggregate_roots/consumer.py
ed_domain/core/aggregate_roots/delivery_job.py
ed_domain/core/aggregate_roots/driver.py
ed_domain/core/aggregate_roots/location.py
ed_domain/core/aggregate_roots/order.py
ed_domain/core/entities/__init__.py
ed_domain/core/entities/api_key.py
ed_domain/core/entities/base_entity.py
ed_domain/core/entities/bill.py
ed_domain/core/entities/car.py
ed_domain/core/entities/notification.py
ed_domain/core/entities/otp.py
ed_domain/core/entities/parcel.py
ed_domain/core/entities/waypoint.py
ed_domain/core/entities/webhook.py
ed_domain/core/value_objects/__init__.py
ed_domain/core/value_objects/base_value_object.py
ed_domain/core/value_objects/length.py
ed_domain/core/value_objects/money.py
ed_domain/core/value_objects/roles.py
ed_domain/documentation/__init__.py
ed_domain/documentation/api/__init__.py
ed_domain/documentation/api/abc_endpoint_client.py
ed_domain/documentation/api/abc_endpoint_descriptions.py
ed_domain/documentation/api/definitions/__init__.py
ed_domain/documentation/api/definitions/api_response.py
ed_domain/documentation/api/definitions/endpoint_call_params.py
ed_domain/documentation/api/definitions/endpoint_description.py
ed_domain/documentation/api/definitions/http_method.py
ed_domain/documentation/message_queue/__init__.py
ed_domain/documentation/message_queue/rabbitmq/__init__.py
ed_domain/documentation/message_queue/rabbitmq/abc_queue_descriptions.py
ed_domain/documentation/message_queue/rabbitmq/abc_queue_producer.py
ed_domain-0.5.5.dist-info/licenses/LICENSE
ed_domain-0.5.5.dist-info/METADATA
ed_domain-0.5.5.dist-info/WHEEL
ed_domain-0.5.5.dist-info/top_level.txt
ed_domain-0.5.5.dist-info/RECORD
